[
    {
        "title": "The Silent Crisis-Climate Change",
        "file": "The Silent Crisis_ Climate Change.mp3",
        "image": "48_Silent Crisis.jpg",
        "volume": 27
    },
    {
        "title": "A True Man",
        "file": "A True Man.mp3",
        "image": "50_TrueMan (1).jpg",
        "volume": 27
    },
    {
        "title": "From Broken Helmets to Billion Dollar Deals-The Untold Cricket Saga",
        "file": "From Broken Helmets to Billion Dollar Deals_ The Untold Cricket Saga.mp3",
        "image": "57_From Broken Helmets to Billion-Dollar Deals_ The Untold Cricket Saga!.jpg",
        "volume": 27
    },
    {
        "title": "Letter to Krishna",
        "file": "Letter to Krishna.mp3",
        "image": "59_Letter_to_krishna.jpg",
        "volume": 27
    },
    {
        "title": "Textile_ India's Treasured Possession",
        "file": "Textile_ India's Treasured Possession.mp3",
        "image": "45_Textile.jpg",
        "volume": 27
    },
    {
        "title": "The Future of Passwords",
        "file": "The Future of Passwords.mp3",
        "image": "54_Future of Passwords.jpg",
        "volume": 27
    },
    {
        "title": "The Science Behind Mindfulness",
        "file": "The Science Behind Mindfulness 1.mp3",
        "image": "44_THe science behind mindfullness.jpg",
        "volume": 27
    },
    {
        "title": "Timeless Wisdom_ Decoding the Concept of prahar",
        "file": "Timeless Wisdom_ Decoding the Concept of prahar.mp3",
        "image": "42_Timeless Wisdom Decoding the Concept of Prahar.jpg",
        "volume": 27
    },
    {
        "title": "Trump Tariffs and Trade War",
        "file": "Trump Tariffs and Trade War.mp3",
        "image": "51_Trump,Tariffs and Trade War_new_1.jpg",
        "volume": 27
    },

    {
        "title": "What Is Even Ordinary",
        "file": "What Is Even Ordinary.mp3",
        "image": "49_What_is_Even_Ordinary.jpg",
        "volume": 27
    }
]